object_validation/__init__.py
object_validation/validators.py
object_validation-0.0.1.dist-info/LICENSE.txt
object_validation-0.0.1.dist-info/METADATA
object_validation-0.0.1.dist-info/RECORD
object_validation-0.0.1.dist-info/WHEEL
object_validation-0.0.1.dist-info/top_level.txt
