Metadata-Version: 2.1
Name: object-validation
Version: 0.0.1
Summary: An object schema validation
Home-page: https://github.com/darrikonn/object-validation
Author: Darri Steinn Konn Konradsson
Author-email: darrikonn@gmail.com
License: MIT
Project-URL: Source, https://github.com/darrikonn/object-validation
Keywords: object schema validation
Platform: UNKNOWN
Classifier: Development Status :: 4 - Beta
Classifier: License :: OSI Approved :: MIT License
Classifier: Programming Language :: Python :: 2
Classifier: Programming Language :: Python :: 2.7
Classifier: Programming Language :: Python :: 3
Classifier: Programming Language :: Python :: 3.4
Classifier: Programming Language :: Python :: 3.5
Classifier: Programming Language :: Python :: 3.6
